salinity/__init__.py
salinity/app.py
salinity/log_utils.py
salinity/parser.py
salinity-0.1.3.dist-info/METADATA
salinity-0.1.3.dist-info/WHEEL
salinity-0.1.3.dist-info/entry_points.txt
salinity-0.1.3.dist-info/top_level.txt
salinity-0.1.3.dist-info/RECORD
