Metadata-Version: 2.1
Name: salinity
Version: 0.1.3
Summary: Analyzes Salt's highstate output and produces a report.
Home-page: https://github.com/urbas/salinity
Author: Matej Urbas
Author-email: matej.urbas@gmail.com
License: UNKNOWN
Keywords: salinity
Platform: UNKNOWN
Classifier: Intended Audience :: Developers
Classifier: License :: OSI Approved :: MIT License
Classifier: Natural Language :: English
Classifier: Programming Language :: Python :: 3.7
Requires-Dist: click (>=7.0)
